setup.py
bin/blockstack-server
blockstack/__init__.py
blockstack/blockstackd.py
blockstack/version.py
blockstack/lib/__init__.py
blockstack/lib/atlas.py
blockstack/lib/b40.py
blockstack/lib/config.py
blockstack/lib/consensus.py
blockstack/lib/hashing.py
blockstack/lib/scripts.py
blockstack/lib/nameset/__init__.py
blockstack/lib/nameset/db.py
blockstack/lib/nameset/namedb.py
blockstack/lib/nameset/virtualchain_hooks.py
blockstack/lib/operations/__init__.py
blockstack/lib/operations/announce.py
blockstack/lib/operations/nameimport.py
blockstack/lib/operations/namespacepreorder.py
blockstack/lib/operations/namespaceready.py
blockstack/lib/operations/namespacereveal.py
blockstack/lib/operations/preorder.py
blockstack/lib/operations/register.py
blockstack/lib/operations/revoke.py
blockstack/lib/operations/transfer.py
blockstack/lib/operations/update.py
blockstack/lib/storage/__init__.py
blockstack/lib/storage/auth.py
blockstack/lib/storage/crawl.py
blockstack_server.egg-info/PKG-INFO
blockstack_server.egg-info/SOURCES.txt
blockstack_server.egg-info/dependency_links.txt
blockstack_server.egg-info/not-zip-safe
blockstack_server.egg-info/requires.txt
blockstack_server.egg-info/top_level.txt